{
  "success": true,
  "lastUpdated": "2026-04-25T14:45:36.426Z",
  "totalMatches": 85,
  "matches": [
    {
      "id": 16012152,
      "isElite": true,
      "status": "finished",
      "fixedDate": "2026-04-25",
      "fixedTime": "12:00",
      "timestamp": 1777107600000,
      "broadcaster": "S Sport / beIN Sports",
      "homeTeam": {
        "name": "Alejandro Davidovich Fokina",
        "logos": [
          "https://raw.githubusercontent.com/elfcrzgr/macsaati-backend/main/tennis/logos/es.png"
        ]
      },
      "awayTeam": {
        "name": "Pablo Carreño Busta",
        "logos": [
          "https://raw.githubusercontent.com/elfcrzgr/macsaati-backend/main/tennis/logos/es.png"
        ]
      },
      "homeRank": "24",
      "awayRank": "94",
      "tournamentLogo": "https://raw.githubusercontent.com/elfcrzgr/macsaati-backend/main/tennis/tournament_logos/2374.png",
      "homeScore": "2",
      "awayScore": "0",
      "setScores": "6-3, 6-3",
      "tournament": "Madrid, Spain"
    },
    {
      "id": 16012155,
      "isElite": true,
      "status": "finished",
      "fixedDate": "2026-04-25",
      "fixedTime": "12:00",
      "timestamp": 1777107600000,
      "broadcaster": "S Sport / beIN Sports",
      "homeTeam": {
        "name": "Francisco Cerundolo",
        "logos": [
          "https://raw.githubusercontent.com/elfcrzgr/macsaati-backend/main/tennis/logos/ar.png"
        ]
      },
      "awayTeam": {
        "name": "Yannick Hanfmann",
        "logos": [
          "https://raw.githubusercontent.com/elfcrzgr/macsaati-backend/main/tennis/logos/de.png"
        ]
      },
      "homeRank": "20",
      "awayRank": "60",
      "tournamentLogo": "https://raw.githubusercontent.com/elfcrzgr/macsaati-backend/main/tennis/tournament_logos/2374.png",
      "homeScore": "2",
      "awayScore": "0",
      "setScores": "6-1, 7-5",
      "tournament": "Madrid, Spain"
    },
    {
      "id": 16012171,
      "isElite": true,
      "status": "finished",
      "fixedDate": "2026-04-25",
      "fixedTime": "12:00",
      "timestamp": 1777107600000,
      "broadcaster": "S Sport / beIN Sports",
      "homeTeam": {
        "name": "Karen Khachanov",
        "logos": [
          "https://raw.githubusercontent.com/elfcrzgr/macsaati-backend/main/tennis/logos/ru.png"
        ]
      },
      "awayTeam": {
        "name": "Adam Walton",
        "logos": [
          "https://raw.githubusercontent.com/elfcrzgr/macsaati-backend/main/tennis/logos/au.png"
        ]
      },
      "homeRank": "16",
      "awayRank": "117",
      "tournamentLogo": "https://raw.githubusercontent.com/elfcrzgr/macsaati-backend/main/tennis/tournament_logos/2374.png",
      "homeScore": "2",
      "awayScore": "0",
      "setScores": "6-2, 6-3",
      "tournament": "Madrid, Spain"
    },
    {
      "id": 16012105,
      "isElite": true,
      "status": "finished",
      "fixedDate": "2026-04-25",
      "fixedTime": "12:00",
      "timestamp": 1777107600000,
      "broadcaster": "S Sport / beIN Sports",
      "homeTeam": {
        "name": "Belinda Bencic",
        "logos": [
          "https://raw.githubusercontent.com/elfcrzgr/macsaati-backend/main/tennis/logos/ch.png"
        ]
      },
      "awayTeam": {
        "name": "Diana Shnaider",
        "logos": [
          "https://raw.githubusercontent.com/elfcrzgr/macsaati-backend/main/tennis/logos/ru.png"
        ]
      },
      "homeRank": "12",
      "awayRank": "19",
      "tournamentLogo": "https://raw.githubusercontent.com/elfcrzgr/macsaati-backend/main/tennis/tournament_logos/2607.png",
      "homeScore": "2",
      "awayScore": "0",
      "setScores": "6-2, 7-6",
      "tournament": "Madrid, Spain"
    },
    {
      "id": 16012127,
      "isElite": true,
      "status": "finished",
      "fixedDate": "2026-04-25",
      "fixedTime": "12:00",
      "timestamp": 1777107600000,
      "broadcaster": "S Sport / beIN Sports",
      "homeTeam": {
        "name": "Laura Samson",
        "logos": [
          "https://raw.githubusercontent.com/elfcrzgr/macsaati-backend/main/tennis/logos/cz.png"
        ]
      },
      "awayTeam": {
        "name": "Anna Bondar",
        "logos": [
          "https://raw.githubusercontent.com/elfcrzgr/macsaati-backend/main/tennis/logos/hu.png"
        ]
      },
      "homeRank": "171",
      "awayRank": "63",
      "tournamentLogo": "https://raw.githubusercontent.com/elfcrzgr/macsaati-backend/main/tennis/tournament_logos/2607.png",
      "homeScore": "0",
      "awayScore": "2",
      "setScores": "6-7, 1-6",
      "tournament": "Madrid, Spain"
    },
    {
      "id": 16048600,
      "isElite": true,
      "status": "finished",
      "fixedDate": "2026-04-25",
      "fixedTime": "12:00",
      "timestamp": 1777107600000,
      "broadcaster": "S Sport / beIN Sports",
      "homeTeam": {
        "name": "Hozumi E / Wu F",
        "logos": [
          "https://raw.githubusercontent.com/elfcrzgr/macsaati-backend/main/tennis/logos/jp.png",
          "https://raw.githubusercontent.com/elfcrzgr/macsaati-backend/main/tennis/logos/tw.png"
        ]
      },
      "awayTeam": {
        "name": "Bucsa C / Melichar-Martinez N",
        "logos": [
          "https://raw.githubusercontent.com/elfcrzgr/macsaati-backend/main/tennis/logos/es.png",
          "https://raw.githubusercontent.com/elfcrzgr/macsaati-backend/main/tennis/logos/us.png"
        ]
      },
      "homeRank": null,
      "awayRank": null,
      "tournamentLogo": "https://raw.githubusercontent.com/elfcrzgr/macsaati-backend/main/tennis/tournament_logos/2609.png",
      "homeScore": "0",
      "awayScore": "2",
      "setScores": "2-6, 4-6",
      "tournament": "Madrid, Spain, Doubles"
    },
    {
      "id": 16048591,
      "isElite": true,
      "status": "finished",
      "fixedDate": "2026-04-25",
      "fixedTime": "12:00",
      "timestamp": 1777107600000,
      "broadcaster": "S Sport / beIN Sports",
      "homeTeam": {
        "name": "Hsieh S-W / Kenin S",
        "logos": [
          "https://raw.githubusercontent.com/elfcrzgr/macsaati-backend/main/tennis/logos/tw.png",
          "https://raw.githubusercontent.com/elfcrzgr/macsaati-backend/main/tennis/logos/us.png"
        ]
      },
      "awayTeam": {
        "name": "Mihalikova T / Nicholls O",
        "logos": [
          "https://raw.githubusercontent.com/elfcrzgr/macsaati-backend/main/tennis/logos/sk.png",
          "https://raw.githubusercontent.com/elfcrzgr/macsaati-backend/main/tennis/logos/gb.png"
        ]
      },
      "homeRank": null,
      "awayRank": null,
      "tournamentLogo": "https://raw.githubusercontent.com/elfcrzgr/macsaati-backend/main/tennis/tournament_logos/2609.png",
      "homeScore": "2",
      "awayScore": "0",
      "setScores": "6-2, 6-3",
      "tournament": "Madrid, Spain, Doubles"
    },
    {
      "id": 16048589,
      "isElite": true,
      "status": "finished",
      "fixedDate": "2026-04-25",
      "fixedTime": "13:30",
      "timestamp": 1777113000000,
      "broadcaster": "S Sport / beIN Sports",
      "homeTeam": {
        "name": "Danilina A / Muhammad A",
        "logos": [
          "https://raw.githubusercontent.com/elfcrzgr/macsaati-backend/main/tennis/logos/kz.png",
          "https://raw.githubusercontent.com/elfcrzgr/macsaati-backend/main/tennis/logos/us.png"
        ]
      },
      "awayTeam": {
        "name": "Eikeri U / Gleason Q",
        "logos": [
          "https://raw.githubusercontent.com/elfcrzgr/macsaati-backend/main/tennis/logos/no.png",
          "https://raw.githubusercontent.com/elfcrzgr/macsaati-backend/main/tennis/logos/us.png"
        ]
      },
      "homeRank": null,
      "awayRank": null,
      "tournamentLogo": "https://raw.githubusercontent.com/elfcrzgr/macsaati-backend/main/tennis/tournament_logos/2609.png",
      "homeScore": "0",
      "awayScore": "2",
      "setScores": "2-6, 1-6",
      "tournament": "Madrid, Spain, Doubles"
    },
    {
      "id": 16048601,
      "isElite": true,
      "status": "finished",
      "fixedDate": "2026-04-25",
      "fixedTime": "13:40",
      "timestamp": 1777113600000,
      "broadcaster": "S Sport / beIN Sports",
      "homeTeam": {
        "name": "Bouzkova M / Noskova L",
        "logos": [
          "https://raw.githubusercontent.com/elfcrzgr/macsaati-backend/main/tennis/logos/cz.png",
          "https://raw.githubusercontent.com/elfcrzgr/macsaati-backend/main/tennis/logos/cz.png"
        ]
      },
      "awayTeam": {
        "name": "Ostapenko J / Routliffe E",
        "logos": [
          "https://raw.githubusercontent.com/elfcrzgr/macsaati-backend/main/tennis/logos/lv.png",
          "https://raw.githubusercontent.com/elfcrzgr/macsaati-backend/main/tennis/logos/nz.png"
        ]
      },
      "homeRank": null,
      "awayRank": null,
      "tournamentLogo": "https://raw.githubusercontent.com/elfcrzgr/macsaati-backend/main/tennis/tournament_logos/2609.png",
      "homeScore": "2",
      "awayScore": "1",
      "setScores": "6-7, 7-5, 10-6",
      "tournament": "Madrid, Spain, Doubles"
    },
    {
      "id": 16012119,
      "isElite": true,
      "status": "finished",
      "fixedDate": "2026-04-25",
      "fixedTime": "13:45",
      "timestamp": 1777113900000,
      "broadcaster": "S Sport / beIN Sports",
      "homeTeam": {
        "name": "Leylah Fernandez",
        "logos": [
          "https://raw.githubusercontent.com/elfcrzgr/macsaati-backend/main/tennis/logos/ca.png"
        ]
      },
      "awayTeam": {
        "name": "Iva Jovic",
        "logos": [
          "https://raw.githubusercontent.com/elfcrzgr/macsaati-backend/main/tennis/logos/us.png"
        ]
      },
      "homeRank": "25",
      "awayRank": "16",
      "tournamentLogo": "https://raw.githubusercontent.com/elfcrzgr/macsaati-backend/main/tennis/tournament_logos/2607.png",
      "homeScore": "2",
      "awayScore": "1",
      "setScores": "3-6, 6-3, 6-2",
      "tournament": "Madrid, Spain"
    },
    {
      "id": 16012151,
      "isElite": true,
      "status": "finished",
      "fixedDate": "2026-04-25",
      "fixedTime": "14:00",
      "timestamp": 1777114800000,
      "broadcaster": "S Sport / beIN Sports",
      "homeTeam": {
        "name": "Juan Manuel Cerundolo",
        "logos": [
          "https://raw.githubusercontent.com/elfcrzgr/macsaati-backend/main/tennis/logos/ar.png"
        ]
      },
      "awayTeam": {
        "name": "Luciano Darderi",
        "logos": [
          "https://raw.githubusercontent.com/elfcrzgr/macsaati-backend/main/tennis/logos/it.png"
        ]
      },
      "homeRank": "67",
      "awayRank": "22",
      "tournamentLogo": "https://raw.githubusercontent.com/elfcrzgr/macsaati-backend/main/tennis/tournament_logos/2374.png",
      "homeScore": "0",
      "awayScore": "2",
      "setScores": "1-6, 3-6",
      "tournament": "Madrid, Spain"
    },
    {
      "id": 16012174,
      "isElite": true,
      "status": "finished",
      "fixedDate": "2026-04-25",
      "fixedTime": "14:00",
      "timestamp": 1777114800000,
      "broadcaster": "S Sport / beIN Sports",
      "homeTeam": {
        "name": "Martin Damm Jr",
        "logos": [
          "https://raw.githubusercontent.com/elfcrzgr/macsaati-backend/main/tennis/logos/us.png"
        ]
      },
      "awayTeam": {
        "name": "Jakub Menšik",
        "logos": [
          "https://raw.githubusercontent.com/elfcrzgr/macsaati-backend/main/tennis/logos/cz.png"
        ]
      },
      "homeRank": "126",
      "awayRank": "27",
      "tournamentLogo": "https://raw.githubusercontent.com/elfcrzgr/macsaati-backend/main/tennis/tournament_logos/2374.png",
      "homeScore": "0",
      "awayScore": "2",
      "setScores": "3-6, 4-6",
      "tournament": "Madrid, Spain"
    },
    {
      "id": 16012125,
      "isElite": true,
      "status": "finished",
      "fixedDate": "2026-04-25",
      "fixedTime": "14:00",
      "timestamp": 1777114800000,
      "broadcaster": "S Sport / beIN Sports",
      "homeTeam": {
        "name": "Mirra Andreeva",
        "logos": [
          "https://raw.githubusercontent.com/elfcrzgr/macsaati-backend/main/tennis/logos/ru.png"
        ]
      },
      "awayTeam": {
        "name": "Dalma Galfi",
        "logos": [
          "https://raw.githubusercontent.com/elfcrzgr/macsaati-backend/main/tennis/logos/hu.png"
        ]
      },
      "homeRank": "8",
      "awayRank": "117",
      "tournamentLogo": "https://raw.githubusercontent.com/elfcrzgr/macsaati-backend/main/tennis/tournament_logos/2607.png",
      "homeScore": "2",
      "awayScore": "0",
      "setScores": "6-3, 6-2",
      "tournament": "Madrid, Spain"
    },
    {
      "id": 16012150,
      "isElite": true,
      "status": "finished",
      "fixedDate": "2026-04-25",
      "fixedTime": "14:10",
      "timestamp": 1777115400000,
      "broadcaster": "S Sport / beIN Sports",
      "homeTeam": {
        "name": "Jaume Munar",
        "logos": [
          "https://raw.githubusercontent.com/elfcrzgr/macsaati-backend/main/tennis/logos/es.png"
        ]
      },
      "awayTeam": {
        "name": "Casper Ruud",
        "logos": [
          "https://raw.githubusercontent.com/elfcrzgr/macsaati-backend/main/tennis/logos/no.png"
        ]
      },
      "homeRank": "38",
      "awayRank": "15",
      "tournamentLogo": "https://raw.githubusercontent.com/elfcrzgr/macsaati-backend/main/tennis/tournament_logos/2374.png",
      "homeScore": "0",
      "awayScore": "2",
      "setScores": "0-6, 1-6",
      "tournament": "Madrid, Spain"
    },
    {
      "id": 16048593,
      "isElite": true,
      "status": "finished",
      "fixedDate": "2026-04-25",
      "fixedTime": "14:30",
      "timestamp": 1777116600000,
      "broadcaster": "S Sport / beIN Sports",
      "homeTeam": {
        "name": "Kato M / Samsonova L",
        "logos": [
          "https://raw.githubusercontent.com/elfcrzgr/macsaati-backend/main/tennis/logos/jp.png",
          "https://raw.githubusercontent.com/elfcrzgr/macsaati-backend/main/tennis/logos/ru.png"
        ]
      },
      "awayTeam": {
        "name": "Kozyreva M / Skoch M",
        "logos": [
          "https://raw.githubusercontent.com/elfcrzgr/macsaati-backend/main/tennis/logos/ru.png",
          "https://raw.githubusercontent.com/elfcrzgr/macsaati-backend/main/tennis/logos/cz.png"
        ]
      },
      "homeRank": null,
      "awayRank": null,
      "tournamentLogo": "https://raw.githubusercontent.com/elfcrzgr/macsaati-backend/main/tennis/tournament_logos/2609.png",
      "homeScore": "0",
      "awayScore": "0",
      "setScores": "",
      "tournament": "Madrid, Spain, Doubles"
    },
    {
      "id": 16012054,
      "isElite": false,
      "status": "finished",
      "fixedDate": "2026-04-25",
      "fixedTime": "14:30",
      "timestamp": 1777116600000,
      "broadcaster": "Tennis TV / Resmi Yayıncı",
      "homeTeam": {
        "name": "Fiona Ferro",
        "logos": [
          "https://raw.githubusercontent.com/elfcrzgr/macsaati-backend/main/tennis/logos/fr.png"
        ]
      },
      "awayTeam": {
        "name": "Linda Klimovicova",
        "logos": [
          "https://raw.githubusercontent.com/elfcrzgr/macsaati-backend/main/tennis/logos/pl.png"
        ]
      },
      "homeRank": "246",
      "awayRank": "160",
      "tournamentLogo": "https://raw.githubusercontent.com/elfcrzgr/macsaati-backend/main/tennis/tournament_logos/34228.png",
      "homeScore": "2",
      "awayScore": "0",
      "setScores": "6-3, 6-4",
      "tournament": "Oeiras 4, Portugal"
    },
    {
      "id": 16018911,
      "isElite": true,
      "status": "finished",
      "fixedDate": "2026-04-25",
      "fixedTime": "14:45",
      "timestamp": 1777117500000,
      "broadcaster": "S Sport / beIN Sports",
      "homeTeam": {
        "name": "Eala A / Sonmez Z",
        "logos": [
          "https://raw.githubusercontent.com/elfcrzgr/macsaati-backend/main/tennis/logos/ph.png",
          "https://raw.githubusercontent.com/elfcrzgr/macsaati-backend/main/tennis/logos/tr.png"
        ]
      },
      "awayTeam": {
        "name": "Siniakova K / Townsend T",
        "logos": [
          "https://raw.githubusercontent.com/elfcrzgr/macsaati-backend/main/tennis/logos/cz.png",
          "https://raw.githubusercontent.com/elfcrzgr/macsaati-backend/main/tennis/logos/us.png"
        ]
      },
      "homeRank": null,
      "awayRank": null,
      "tournamentLogo": "https://raw.githubusercontent.com/elfcrzgr/macsaati-backend/main/tennis/tournament_logos/2609.png",
      "homeScore": "0",
      "awayScore": "2",
      "setScores": "1-6, 5-7",
      "tournament": "Madrid, Spain, Doubles"
    },
    {
      "id": 16012065,
      "isElite": false,
      "status": "finished",
      "fixedDate": "2026-04-25",
      "fixedTime": "14:50",
      "timestamp": 1777117800000,
      "broadcaster": "Tennis TV / Resmi Yayıncı",
      "homeTeam": {
        "name": "Kempen M / Salden L",
        "logos": [
          "https://raw.githubusercontent.com/elfcrzgr/macsaati-backend/main/tennis/logos/be.png",
          "https://raw.githubusercontent.com/elfcrzgr/macsaati-backend/main/tennis/logos/be.png"
        ]
      },
      "awayTeam": {
        "name": "Costoulas S / Jorge M",
        "logos": [
          "https://raw.githubusercontent.com/elfcrzgr/macsaati-backend/main/tennis/logos/be.png",
          "https://raw.githubusercontent.com/elfcrzgr/macsaati-backend/main/tennis/logos/pt.png"
        ]
      },
      "homeRank": null,
      "awayRank": null,
      "tournamentLogo": "https://raw.githubusercontent.com/elfcrzgr/macsaati-backend/main/tennis/tournament_logos/34229.png",
      "homeScore": "0",
      "awayScore": "2",
      "setScores": "4-6, 2-6",
      "tournament": "Oeiras 4, Portugal, Doubles"
    },
    {
      "id": 16013100,
      "isElite": true,
      "status": "finished",
      "fixedDate": "2026-04-25",
      "fixedTime": "15:25",
      "timestamp": 1777119900000,
      "broadcaster": "S Sport / beIN Sports",
      "homeTeam": {
        "name": "Brandon Nakashima",
        "logos": [
          "https://raw.githubusercontent.com/elfcrzgr/macsaati-backend/main/tennis/logos/us.png"
        ]
      },
      "awayTeam": {
        "name": "Alexander Blockx",
        "logos": [
          "https://raw.githubusercontent.com/elfcrzgr/macsaati-backend/main/tennis/logos/be.png"
        ]
      },
      "homeRank": "32",
      "awayRank": "69",
      "tournamentLogo": "https://raw.githubusercontent.com/elfcrzgr/macsaati-backend/main/tennis/tournament_logos/2374.png",
      "homeScore": "1",
      "awayScore": "2",
      "setScores": "6-3, 3-6, 4-6",
      "tournament": "Madrid, Spain"
    },
    {
      "id": 16012169,
      "isElite": true,
      "status": "inprogress",
      "fixedDate": "2026-04-25",
      "fixedTime": "15:35",
      "timestamp": 1777120500000,
      "broadcaster": "S Sport / beIN Sports",
      "homeTeam": {
        "name": "Ugo Humbert",
        "logos": [
          "https://raw.githubusercontent.com/elfcrzgr/macsaati-backend/main/tennis/logos/fr.png"
        ]
      },
      "awayTeam": {
        "name": "Terence Atmane",
        "logos": [
          "https://raw.githubusercontent.com/elfcrzgr/macsaati-backend/main/tennis/logos/fr.png"
        ]
      },
      "homeRank": "34",
      "awayRank": "47",
      "tournamentLogo": "https://raw.githubusercontent.com/elfcrzgr/macsaati-backend/main/tennis/tournament_logos/2374.png",
      "homeScore": "0",
      "awayScore": "1",
      "setScores": "6-7, 4-5",
      "tournament": "Madrid, Spain"
    },
    {
      "id": 16012101,
      "isElite": true,
      "status": "inprogress",
      "fixedDate": "2026-04-25",
      "fixedTime": "15:45",
      "timestamp": 1777121100000,
      "broadcaster": "S Sport / beIN Sports",
      "homeTeam": {
        "name": "Iga Swiatek",
        "logos": [
          "https://raw.githubusercontent.com/elfcrzgr/macsaati-backend/main/tennis/logos/pl.png"
        ]
      },
      "awayTeam": {
        "name": "Ann Li",
        "logos": [
          "https://raw.githubusercontent.com/elfcrzgr/macsaati-backend/main/tennis/logos/us.png"
        ]
      },
      "homeRank": "4",
      "awayRank": "34",
      "tournamentLogo": "https://raw.githubusercontent.com/elfcrzgr/macsaati-backend/main/tennis/tournament_logos/2607.png",
      "homeScore": "1",
      "awayScore": "1",
      "setScores": "6-7, 6-2, 0-0",
      "tournament": "Madrid, Spain"
    },
    {
      "id": 16048596,
      "isElite": true,
      "status": "finished",
      "fixedDate": "2026-04-25",
      "fixedTime": "16:00",
      "timestamp": 1777122000000,
      "broadcaster": "S Sport / beIN Sports",
      "homeTeam": {
        "name": "Jiang X / Xu Y",
        "logos": [
          "https://raw.githubusercontent.com/elfcrzgr/macsaati-backend/main/tennis/logos/cn.png",
          "https://raw.githubusercontent.com/elfcrzgr/macsaati-backend/main/tennis/logos/cn.png"
        ]
      },
      "awayTeam": {
        "name": "Boulter K / Williams V",
        "logos": [
          "https://raw.githubusercontent.com/elfcrzgr/macsaati-backend/main/tennis/logos/gb.png",
          "https://raw.githubusercontent.com/elfcrzgr/macsaati-backend/main/tennis/logos/us.png"
        ]
      },
      "homeRank": null,
      "awayRank": null,
      "tournamentLogo": "https://raw.githubusercontent.com/elfcrzgr/macsaati-backend/main/tennis/tournament_logos/2609.png",
      "homeScore": "1",
      "awayScore": "2",
      "setScores": "6-4, 3-6, 7-10",
      "tournament": "Madrid, Spain, Doubles"
    },
    {
      "id": 16013094,
      "isElite": true,
      "status": "finished",
      "fixedDate": "2026-04-25",
      "fixedTime": "16:10",
      "timestamp": 1777122600000,
      "broadcaster": "S Sport / beIN Sports",
      "homeTeam": {
        "name": "Vilius Gaubas",
        "logos": [
          "https://raw.githubusercontent.com/elfcrzgr/macsaati-backend/main/tennis/logos/lt.png"
        ]
      },
      "awayTeam": {
        "name": "Felix Auger-Aliassime",
        "logos": [
          "https://raw.githubusercontent.com/elfcrzgr/macsaati-backend/main/tennis/logos/ca.png"
        ]
      },
      "homeRank": "124",
      "awayRank": "5",
      "tournamentLogo": "https://raw.githubusercontent.com/elfcrzgr/macsaati-backend/main/tennis/tournament_logos/2374.png",
      "homeScore": "0",
      "awayScore": "2",
      "setScores": "3-6, 4-6",
      "tournament": "Madrid, Spain"
    },
    {
      "id": 16012173,
      "isElite": true,
      "status": "notstarted",
      "fixedDate": "2026-04-25",
      "fixedTime": "16:45",
      "timestamp": 1777124700000,
      "broadcaster": "S Sport / beIN Sports",
      "homeTeam": {
        "name": "Learner Tien",
        "logos": [
          "https://raw.githubusercontent.com/elfcrzgr/macsaati-backend/main/tennis/logos/us.png"
        ]
      },
      "awayTeam": {
        "name": "Adolfo Daniel Vallejo",
        "logos": [
          "https://raw.githubusercontent.com/elfcrzgr/macsaati-backend/main/tennis/logos/py.png"
        ]
      },
      "homeRank": "21",
      "awayRank": "96",
      "tournamentLogo": "https://raw.githubusercontent.com/elfcrzgr/macsaati-backend/main/tennis/tournament_logos/2374.png",
      "homeScore": "-",
      "awayScore": "-",
      "setScores": "",
      "tournament": "Madrid, Spain"
    },
    {
      "id": 16012175,
      "isElite": true,
      "status": "inprogress",
      "fixedDate": "2026-04-25",
      "fixedTime": "17:00",
      "timestamp": 1777125600000,
      "broadcaster": "S Sport / beIN Sports",
      "homeTeam": {
        "name": "Mariano Navone",
        "logos": [
          "https://raw.githubusercontent.com/elfcrzgr/macsaati-backend/main/tennis/logos/ar.png"
        ]
      },
      "awayTeam": {
        "name": "Alexander Zverev",
        "logos": [
          "https://raw.githubusercontent.com/elfcrzgr/macsaati-backend/main/tennis/logos/de.png"
        ]
      },
      "homeRank": "45",
      "awayRank": "3",
      "tournamentLogo": "https://raw.githubusercontent.com/elfcrzgr/macsaati-backend/main/tennis/tournament_logos/2374.png",
      "homeScore": "0",
      "awayScore": "1",
      "setScores": "1-6, 2-0",
      "tournament": "Madrid, Spain"
    },
    {
      "id": 16012103,
      "isElite": true,
      "status": "notstarted",
      "fixedDate": "2026-04-25",
      "fixedTime": "17:20",
      "timestamp": 1777126800000,
      "broadcaster": "S Sport / beIN Sports",
      "homeTeam": {
        "name": "Hailey Baptiste",
        "logos": [
          "https://raw.githubusercontent.com/elfcrzgr/macsaati-backend/main/tennis/logos/us.png"
        ]
      },
      "awayTeam": {
        "name": "Jasmine Paolini",
        "logos": [
          "https://raw.githubusercontent.com/elfcrzgr/macsaati-backend/main/tennis/logos/it.png"
        ]
      },
      "homeRank": "32",
      "awayRank": "9",
      "tournamentLogo": "https://raw.githubusercontent.com/elfcrzgr/macsaati-backend/main/tennis/tournament_logos/2607.png",
      "homeScore": "-",
      "awayScore": "-",
      "setScores": "",
      "tournament": "Madrid, Spain"
    },
    {
      "id": 16018908,
      "isElite": true,
      "status": "inprogress",
      "fixedDate": "2026-04-25",
      "fixedTime": "17:30",
      "timestamp": 1777127400000,
      "broadcaster": "S Sport / beIN Sports",
      "homeTeam": {
        "name": "Mertens E / Zhang S",
        "logos": [
          "https://raw.githubusercontent.com/elfcrzgr/macsaati-backend/main/tennis/logos/be.png",
          "https://raw.githubusercontent.com/elfcrzgr/macsaati-backend/main/tennis/logos/cn.png"
        ]
      },
      "awayTeam": {
        "name": "Andreeva M / Shnaider D",
        "logos": [
          "https://raw.githubusercontent.com/elfcrzgr/macsaati-backend/main/tennis/logos/ru.png",
          "https://raw.githubusercontent.com/elfcrzgr/macsaati-backend/main/tennis/logos/ru.png"
        ]
      },
      "homeRank": null,
      "awayRank": null,
      "tournamentLogo": "https://raw.githubusercontent.com/elfcrzgr/macsaati-backend/main/tennis/tournament_logos/2609.png",
      "homeScore": "0",
      "awayScore": "0",
      "setScores": "0-0",
      "tournament": "Madrid, Spain, Doubles"
    },
    {
      "id": 16012172,
      "isElite": true,
      "status": "notstarted",
      "fixedDate": "2026-04-25",
      "fixedTime": "17:40",
      "timestamp": 1777128000000,
      "broadcaster": "S Sport / beIN Sports",
      "homeTeam": {
        "name": "Camilo Ugo Carabelli",
        "logos": [
          "https://raw.githubusercontent.com/elfcrzgr/macsaati-backend/main/tennis/logos/ar.png"
        ]
      },
      "awayTeam": {
        "name": "Flavio Cobolli",
        "logos": [
          "https://raw.githubusercontent.com/elfcrzgr/macsaati-backend/main/tennis/logos/it.png"
        ]
      },
      "homeRank": "57",
      "awayRank": "13",
      "tournamentLogo": "https://raw.githubusercontent.com/elfcrzgr/macsaati-backend/main/tennis/tournament_logos/2374.png",
      "homeScore": "-",
      "awayScore": "-",
      "setScores": "",
      "tournament": "Madrid, Spain"
    },
    {
      "id": 16048604,
      "isElite": true,
      "status": "notstarted",
      "fixedDate": "2026-04-25",
      "fixedTime": "17:45",
      "timestamp": 1777128300000,
      "broadcaster": "S Sport / beIN Sports",
      "homeTeam": {
        "name": "Siegemund L / Zvonareva V",
        "logos": [
          "https://raw.githubusercontent.com/elfcrzgr/macsaati-backend/main/tennis/logos/de.png",
          "https://raw.githubusercontent.com/elfcrzgr/macsaati-backend/main/tennis/logos/ru.png"
        ]
      },
      "awayTeam": {
        "name": "Jovic I / Mboko V",
        "logos": [
          "https://raw.githubusercontent.com/elfcrzgr/macsaati-backend/main/tennis/logos/us.png",
          "https://raw.githubusercontent.com/elfcrzgr/macsaati-backend/main/tennis/logos/ca.png"
        ]
      },
      "homeRank": null,
      "awayRank": null,
      "tournamentLogo": "https://raw.githubusercontent.com/elfcrzgr/macsaati-backend/main/tennis/tournament_logos/2609.png",
      "homeScore": "-",
      "awayScore": "-",
      "setScores": "",
      "tournament": "Madrid, Spain, Doubles"
    },
    {
      "id": 16013097,
      "isElite": true,
      "status": "notstarted",
      "fixedDate": "2026-04-25",
      "fixedTime": "18:15",
      "timestamp": 1777130100000,
      "broadcaster": "S Sport / beIN Sports",
      "homeTeam": {
        "name": "Nicolai Budkov Kjaer",
        "logos": [
          "https://raw.githubusercontent.com/elfcrzgr/macsaati-backend/main/tennis/logos/no.png"
        ]
      },
      "awayTeam": {
        "name": "Denis Shapovalov",
        "logos": [
          "https://raw.githubusercontent.com/elfcrzgr/macsaati-backend/main/tennis/logos/ca.png"
        ]
      },
      "homeRank": "140",
      "awayRank": "35",
      "tournamentLogo": "https://raw.githubusercontent.com/elfcrzgr/macsaati-backend/main/tennis/tournament_logos/2374.png",
      "homeScore": "-",
      "awayScore": "-",
      "setScores": "",
      "tournament": "Madrid, Spain"
    },
    {
      "id": 16012154,
      "isElite": true,
      "status": "notstarted",
      "fixedDate": "2026-04-25",
      "fixedTime": "18:50",
      "timestamp": 1777132200000,
      "broadcaster": "S Sport / beIN Sports",
      "homeTeam": {
        "name": "Daniel Merida",
        "logos": [
          "https://raw.githubusercontent.com/elfcrzgr/macsaati-backend/main/tennis/logos/es.png"
        ]
      },
      "awayTeam": {
        "name": "Corentin Moutet",
        "logos": [
          "https://raw.githubusercontent.com/elfcrzgr/macsaati-backend/main/tennis/logos/fr.png"
        ]
      },
      "homeRank": "102",
      "awayRank": "30",
      "tournamentLogo": "https://raw.githubusercontent.com/elfcrzgr/macsaati-backend/main/tennis/tournament_logos/2374.png",
      "homeScore": "-",
      "awayScore": "-",
      "setScores": "",
      "tournament": "Madrid, Spain"
    },
    {
      "id": 16013096,
      "isElite": true,
      "status": "notstarted",
      "fixedDate": "2026-04-25",
      "fixedTime": "20:00",
      "timestamp": 1777136400000,
      "broadcaster": "S Sport / beIN Sports",
      "homeTeam": {
        "name": "Daniil Medvedev",
        "logos": [
          "https://raw.githubusercontent.com/elfcrzgr/macsaati-backend/main/tennis/logos/ru.png"
        ]
      },
      "awayTeam": {
        "name": "Fábián Marozsán",
        "logos": [
          "https://raw.githubusercontent.com/elfcrzgr/macsaati-backend/main/tennis/logos/hu.png"
        ]
      },
      "homeRank": "10",
      "awayRank": "50",
      "tournamentLogo": "https://raw.githubusercontent.com/elfcrzgr/macsaati-backend/main/tennis/tournament_logos/2374.png",
      "homeScore": "-",
      "awayScore": "-",
      "setScores": "",
      "tournament": "Madrid, Spain"
    },
    {
      "id": 16012104,
      "isElite": true,
      "status": "notstarted",
      "fixedDate": "2026-04-25",
      "fixedTime": "21:00",
      "timestamp": 1777140000000,
      "broadcaster": "S Sport / beIN Sports",
      "homeTeam": {
        "name": "Aryna Sabalenka",
        "logos": [
          "https://raw.githubusercontent.com/elfcrzgr/macsaati-backend/main/tennis/logos/by.png"
        ]
      },
      "awayTeam": {
        "name": "Jaqueline Cristian",
        "logos": [
          "https://raw.githubusercontent.com/elfcrzgr/macsaati-backend/main/tennis/logos/ro.png"
        ]
      },
      "homeRank": "1",
      "awayRank": "33",
      "tournamentLogo": "https://raw.githubusercontent.com/elfcrzgr/macsaati-backend/main/tennis/tournament_logos/2607.png",
      "homeScore": "-",
      "awayScore": "-",
      "setScores": "",
      "tournament": "Madrid, Spain"
    },
    {
      "id": 16012166,
      "isElite": true,
      "status": "notstarted",
      "fixedDate": "2026-04-25",
      "fixedTime": "22:10",
      "timestamp": 1777144200000,
      "broadcaster": "S Sport / beIN Sports",
      "homeTeam": {
        "name": "Alexander Bublik",
        "logos": [
          "https://raw.githubusercontent.com/elfcrzgr/macsaati-backend/main/tennis/logos/kz.png"
        ]
      },
      "awayTeam": {
        "name": "Stefanos Tsitsipas",
        "logos": [
          "https://raw.githubusercontent.com/elfcrzgr/macsaati-backend/main/tennis/logos/gr.png"
        ]
      },
      "homeRank": "11",
      "awayRank": "80",
      "tournamentLogo": "https://raw.githubusercontent.com/elfcrzgr/macsaati-backend/main/tennis/tournament_logos/2374.png",
      "homeScore": "-",
      "awayScore": "-",
      "setScores": "",
      "tournament": "Madrid, Spain"
    },
    {
      "id": 16012098,
      "isElite": true,
      "status": "notstarted",
      "fixedDate": "2026-04-25",
      "fixedTime": "22:30",
      "timestamp": 1777145400000,
      "broadcaster": "S Sport / beIN Sports",
      "homeTeam": {
        "name": "Anhelina Kalinina",
        "logos": [
          "https://raw.githubusercontent.com/elfcrzgr/macsaati-backend/main/tennis/logos/ua.png"
        ]
      },
      "awayTeam": {
        "name": "Naomi Osaka",
        "logos": [
          "https://raw.githubusercontent.com/elfcrzgr/macsaati-backend/main/tennis/logos/jp.png"
        ]
      },
      "homeRank": "110",
      "awayRank": "15",
      "tournamentLogo": "https://raw.githubusercontent.com/elfcrzgr/macsaati-backend/main/tennis/tournament_logos/2607.png",
      "homeScore": "-",
      "awayScore": "-",
      "setScores": "",
      "tournament": "Madrid, Spain"
    },
    {
      "id": 16069224,
      "isElite": false,
      "status": "notstarted",
      "fixedDate": "2026-04-26",
      "fixedTime": "06:00",
      "timestamp": 1777172400000,
      "broadcaster": "Tennis TV / Resmi Yayıncı",
      "homeTeam": {
        "name": "Rada Zolotareva",
        "logos": [
          "https://raw.githubusercontent.com/elfcrzgr/macsaati-backend/main/tennis/logos/ru.png"
        ]
      },
      "awayTeam": {
        "name": "Ye Qiuyu",
        "logos": [
          "https://raw.githubusercontent.com/elfcrzgr/macsaati-backend/main/tennis/logos/cn.png"
        ]
      },
      "homeRank": "439",
      "awayRank": "1104",
      "tournamentLogo": "https://raw.githubusercontent.com/elfcrzgr/macsaati-backend/main/tennis/tournament_logos/29214.png",
      "homeScore": "-",
      "awayScore": "-",
      "setScores": "",
      "tournament": "Huzhou, China Qualifying"
    },
    {
      "id": 16069194,
      "isElite": false,
      "status": "notstarted",
      "fixedDate": "2026-04-26",
      "fixedTime": "06:00",
      "timestamp": 1777172400000,
      "broadcaster": "Tennis TV / Resmi Yayıncı",
      "homeTeam": {
        "name": "Zhang-Qian Wei",
        "logos": [
          "https://raw.githubusercontent.com/elfcrzgr/macsaati-backend/main/tennis/logos/cn.png"
        ]
      },
      "awayTeam": {
        "name": "Ikumi Yamazaki",
        "logos": [
          "https://raw.githubusercontent.com/elfcrzgr/macsaati-backend/main/tennis/logos/jp.png"
        ]
      },
      "homeRank": null,
      "awayRank": "457",
      "tournamentLogo": "https://raw.githubusercontent.com/elfcrzgr/macsaati-backend/main/tennis/tournament_logos/29214.png",
      "homeScore": "-",
      "awayScore": "-",
      "setScores": "",
      "tournament": "Huzhou, China Qualifying"
    },
    {
      "id": 16069190,
      "isElite": false,
      "status": "notstarted",
      "fixedDate": "2026-04-26",
      "fixedTime": "07:00",
      "timestamp": 1777176000000,
      "broadcaster": "Tennis TV / Resmi Yayıncı",
      "homeTeam": {
        "name": "Hiroko Kuwata",
        "logos": [
          "https://raw.githubusercontent.com/elfcrzgr/macsaati-backend/main/tennis/logos/jp.png"
        ]
      },
      "awayTeam": {
        "name": "Meiqi Guo",
        "logos": [
          "https://raw.githubusercontent.com/elfcrzgr/macsaati-backend/main/tennis/logos/cn.png"
        ]
      },
      "homeRank": "668",
      "awayRank": "484",
      "tournamentLogo": "https://raw.githubusercontent.com/elfcrzgr/macsaati-backend/main/tennis/tournament_logos/29214.png",
      "homeScore": "-",
      "awayScore": "-",
      "setScores": "",
      "tournament": "Huzhou, China Qualifying"
    },
    {
      "id": 16069226,
      "isElite": false,
      "status": "notstarted",
      "fixedDate": "2026-04-26",
      "fixedTime": "07:10",
      "timestamp": 1777176600000,
      "broadcaster": "Tennis TV / Resmi Yayıncı",
      "homeTeam": {
        "name": "Jiaqi Wang",
        "logos": [
          "https://raw.githubusercontent.com/elfcrzgr/macsaati-backend/main/tennis/logos/cn.png"
        ]
      },
      "awayTeam": {
        "name": "Peangtarn Plipuech",
        "logos": [
          "https://raw.githubusercontent.com/elfcrzgr/macsaati-backend/main/tennis/logos/th.png"
        ]
      },
      "homeRank": "438",
      "awayRank": "733",
      "tournamentLogo": "https://raw.githubusercontent.com/elfcrzgr/macsaati-backend/main/tennis/tournament_logos/29214.png",
      "homeScore": "-",
      "awayScore": "-",
      "setScores": "",
      "tournament": "Huzhou, China Qualifying"
    },
    {
      "id": 16069193,
      "isElite": false,
      "status": "notstarted",
      "fixedDate": "2026-04-26",
      "fixedTime": "07:10",
      "timestamp": 1777176600000,
      "broadcaster": "Tennis TV / Resmi Yayıncı",
      "homeTeam": {
        "name": "Kristiana Sidorova",
        "logos": [
          "https://raw.githubusercontent.com/elfcrzgr/macsaati-backend/main/tennis/logos/ru.png"
        ]
      },
      "awayTeam": {
        "name": "Amy Zhu",
        "logos": [
          "https://raw.githubusercontent.com/elfcrzgr/macsaati-backend/main/tennis/logos/us.png"
        ]
      },
      "homeRank": "380",
      "awayRank": "656",
      "tournamentLogo": "https://raw.githubusercontent.com/elfcrzgr/macsaati-backend/main/tennis/tournament_logos/29214.png",
      "homeScore": "-",
      "awayScore": "-",
      "setScores": "",
      "tournament": "Huzhou, China Qualifying"
    },
    {
      "id": 16069191,
      "isElite": false,
      "status": "notstarted",
      "fixedDate": "2026-04-26",
      "fixedTime": "08:10",
      "timestamp": 1777180200000,
      "broadcaster": "Tennis TV / Resmi Yayıncı",
      "homeTeam": {
        "name": "Zhibek Kulambayeva",
        "logos": [
          "https://raw.githubusercontent.com/elfcrzgr/macsaati-backend/main/tennis/logos/kz.png"
        ]
      },
      "awayTeam": {
        "name": "Shiyu Ye",
        "logos": [
          "https://raw.githubusercontent.com/elfcrzgr/macsaati-backend/main/tennis/logos/cn.png"
        ]
      },
      "homeRank": "395",
      "awayRank": "863",
      "tournamentLogo": "https://raw.githubusercontent.com/elfcrzgr/macsaati-backend/main/tennis/tournament_logos/29214.png",
      "homeScore": "-",
      "awayScore": "-",
      "setScores": "",
      "tournament": "Huzhou, China Qualifying"
    },
    {
      "id": 16069192,
      "isElite": false,
      "status": "notstarted",
      "fixedDate": "2026-04-26",
      "fixedTime": "08:20",
      "timestamp": 1777180800000,
      "broadcaster": "Tennis TV / Resmi Yayıncı",
      "homeTeam": {
        "name": "Huang Yujia",
        "logos": [
          "https://raw.githubusercontent.com/elfcrzgr/macsaati-backend/main/tennis/logos/cn.png"
        ]
      },
      "awayTeam": {
        "name": "Chengyiyi Yuan",
        "logos": [
          "https://raw.githubusercontent.com/elfcrzgr/macsaati-backend/main/tennis/logos/cn.png"
        ]
      },
      "homeRank": "728",
      "awayRank": "643",
      "tournamentLogo": "https://raw.githubusercontent.com/elfcrzgr/macsaati-backend/main/tennis/tournament_logos/29214.png",
      "homeScore": "-",
      "awayScore": "-",
      "setScores": "",
      "tournament": "Huzhou, China Qualifying"
    },
    {
      "id": 16069225,
      "isElite": false,
      "status": "notstarted",
      "fixedDate": "2026-04-26",
      "fixedTime": "09:00",
      "timestamp": 1777183200000,
      "broadcaster": "Tennis TV / Resmi Yayıncı",
      "homeTeam": {
        "name": "Yiming Dang",
        "logos": [
          "https://raw.githubusercontent.com/elfcrzgr/macsaati-backend/main/tennis/logos/cn.png"
        ]
      },
      "awayTeam": {
        "name": "Varvara Panshina",
        "logos": [
          "https://raw.githubusercontent.com/elfcrzgr/macsaati-backend/main/tennis/logos/ru.png"
        ]
      },
      "homeRank": "767",
      "awayRank": "468",
      "tournamentLogo": "https://raw.githubusercontent.com/elfcrzgr/macsaati-backend/main/tennis/tournament_logos/29214.png",
      "homeScore": "-",
      "awayScore": "-",
      "setScores": "",
      "tournament": "Huzhou, China Qualifying"
    },
    {
      "id": 16066003,
      "isElite": true,
      "status": "notstarted",
      "fixedDate": "2026-04-26",
      "fixedTime": "12:00",
      "timestamp": 1777194000000,
      "broadcaster": "S Sport / beIN Sports",
      "homeTeam": {
        "name": "Arevalo M / Pavic M",
        "logos": [
          "https://raw.githubusercontent.com/elfcrzgr/macsaati-backend/main/tennis/logos/sv.png",
          "https://raw.githubusercontent.com/elfcrzgr/macsaati-backend/main/tennis/logos/hr.png"
        ]
      },
      "awayTeam": {
        "name": "Paul T / Quinn E",
        "logos": [
          "https://raw.githubusercontent.com/elfcrzgr/macsaati-backend/main/tennis/logos/us.png",
          "https://raw.githubusercontent.com/elfcrzgr/macsaati-backend/main/tennis/logos/us.png"
        ]
      },
      "homeRank": null,
      "awayRank": null,
      "tournamentLogo": "https://raw.githubusercontent.com/elfcrzgr/macsaati-backend/main/tennis/tournament_logos/2511.png",
      "homeScore": "-",
      "awayScore": "-",
      "setScores": "",
      "tournament": "Madrid, Spain, Doubles"
    },
    {
      "id": 16066012,
      "isElite": true,
      "status": "notstarted",
      "fixedDate": "2026-04-26",
      "fixedTime": "12:00",
      "timestamp": 1777194000000,
      "broadcaster": "S Sport / beIN Sports",
      "homeTeam": {
        "name": "Granollers M / Zeballos H",
        "logos": [
          "https://raw.githubusercontent.com/elfcrzgr/macsaati-backend/main/tennis/logos/es.png",
          "https://raw.githubusercontent.com/elfcrzgr/macsaati-backend/main/tennis/logos/ar.png"
        ]
      },
      "awayTeam": {
        "name": "Arneodo R / Vacherot V",
        "logos": [
          "https://raw.githubusercontent.com/elfcrzgr/macsaati-backend/main/tennis/logos/mc.png",
          "https://raw.githubusercontent.com/elfcrzgr/macsaati-backend/main/tennis/logos/mc.png"
        ]
      },
      "homeRank": null,
      "awayRank": null,
      "tournamentLogo": "https://raw.githubusercontent.com/elfcrzgr/macsaati-backend/main/tennis/tournament_logos/2511.png",
      "homeScore": "-",
      "awayScore": "-",
      "setScores": "",
      "tournament": "Madrid, Spain, Doubles"
    },
    {
      "id": 16013089,
      "isElite": true,
      "status": "notstarted",
      "fixedDate": "2026-04-26",
      "fixedTime": "12:00",
      "timestamp": 1777194000000,
      "broadcaster": "S Sport / beIN Sports",
      "homeTeam": {
        "name": "Jiri Lehečka",
        "logos": [
          "https://raw.githubusercontent.com/elfcrzgr/macsaati-backend/main/tennis/logos/cz.png"
        ]
      },
      "awayTeam": {
        "name": "Alex Michelsen",
        "logos": [
          "https://raw.githubusercontent.com/elfcrzgr/macsaati-backend/main/tennis/logos/us.png"
        ]
      },
      "homeRank": "14",
      "awayRank": "37",
      "tournamentLogo": "https://raw.githubusercontent.com/elfcrzgr/macsaati-backend/main/tennis/tournament_logos/2374.png",
      "homeScore": "-",
      "awayScore": "-",
      "setScores": "",
      "tournament": "Madrid, Spain"
    },
    {
      "id": 16012117,
      "isElite": true,
      "status": "notstarted",
      "fixedDate": "2026-04-26",
      "fixedTime": "12:00",
      "timestamp": 1777194000000,
      "broadcaster": "S Sport / beIN Sports",
      "homeTeam": {
        "name": "Katerina Siniakova",
        "logos": [
          "https://raw.githubusercontent.com/elfcrzgr/macsaati-backend/main/tennis/logos/cz.png"
        ]
      },
      "awayTeam": {
        "name": "Catherine McNally",
        "logos": [
          "https://raw.githubusercontent.com/elfcrzgr/macsaati-backend/main/tennis/logos/us.png"
        ]
      },
      "homeRank": "42",
      "awayRank": "76",
      "tournamentLogo": "https://raw.githubusercontent.com/elfcrzgr/macsaati-backend/main/tennis/tournament_logos/2607.png",
      "homeScore": "-",
      "awayScore": "-",
      "setScores": "",
      "tournament": "Madrid, Spain"
    },
    {
      "id": 16012122,
      "isElite": true,
      "status": "notstarted",
      "fixedDate": "2026-04-26",
      "fixedTime": "12:00",
      "timestamp": 1777194000000,
      "broadcaster": "S Sport / beIN Sports",
      "homeTeam": {
        "name": "Linda Noskova",
        "logos": [
          "https://raw.githubusercontent.com/elfcrzgr/macsaati-backend/main/tennis/logos/cz.png"
        ]
      },
      "awayTeam": {
        "name": "Liudmila Samsonova",
        "logos": [
          "https://raw.githubusercontent.com/elfcrzgr/macsaati-backend/main/tennis/logos/ru.png"
        ]
      },
      "homeRank": "13",
      "awayRank": "20",
      "tournamentLogo": "https://raw.githubusercontent.com/elfcrzgr/macsaati-backend/main/tennis/tournament_logos/2607.png",
      "homeScore": "-",
      "awayScore": "-",
      "setScores": "",
      "tournament": "Madrid, Spain"
    },
    {
      "id": 16012123,
      "isElite": true,
      "status": "notstarted",
      "fixedDate": "2026-04-26",
      "fixedTime": "12:00",
      "timestamp": 1777194000000,
      "broadcaster": "S Sport / beIN Sports",
      "homeTeam": {
        "name": "Solana Sierra",
        "logos": [
          "https://raw.githubusercontent.com/elfcrzgr/macsaati-backend/main/tennis/logos/ar.png"
        ]
      },
      "awayTeam": {
        "name": "Zeynep Sönmez",
        "logos": [
          "https://raw.githubusercontent.com/elfcrzgr/macsaati-backend/main/tennis/logos/tr.png"
        ]
      },
      "homeRank": "88",
      "awayRank": "67",
      "tournamentLogo": "https://raw.githubusercontent.com/elfcrzgr/macsaati-backend/main/tennis/tournament_logos/2607.png",
      "homeScore": "-",
      "awayScore": "-",
      "setScores": "",
      "tournament": "Madrid, Spain"
    },
    {
      "id": 16012124,
      "isElite": true,
      "status": "notstarted",
      "fixedDate": "2026-04-26",
      "fixedTime": "12:00",
      "timestamp": 1777194000000,
      "broadcaster": "S Sport / beIN Sports",
      "homeTeam": {
        "name": "Sorana Cirstea",
        "logos": [
          "https://raw.githubusercontent.com/elfcrzgr/macsaati-backend/main/tennis/logos/ro.png"
        ]
      },
      "awayTeam": {
        "name": "Coco Gauff",
        "logos": [
          "https://raw.githubusercontent.com/elfcrzgr/macsaati-backend/main/tennis/logos/us.png"
        ]
      },
      "homeRank": "26",
      "awayRank": "3",
      "tournamentLogo": "https://raw.githubusercontent.com/elfcrzgr/macsaati-backend/main/tennis/tournament_logos/2607.png",
      "homeScore": "-",
      "awayScore": "-",
      "setScores": "",
      "tournament": "Madrid, Spain"
    },
    {
      "id": 16012056,
      "isElite": false,
      "status": "notstarted",
      "fixedDate": "2026-04-26",
      "fixedTime": "13:00",
      "timestamp": 1777197600000,
      "broadcaster": "Tennis TV / Resmi Yayıncı",
      "homeTeam": {
        "name": "Polina Kudermetova",
        "logos": [
          "https://raw.githubusercontent.com/elfcrzgr/macsaati-backend/main/tennis/logos/uz.png"
        ]
      },
      "awayTeam": {
        "name": "Fiona Ferro",
        "logos": [
          "https://raw.githubusercontent.com/elfcrzgr/macsaati-backend/main/tennis/logos/fr.png"
        ]
      },
      "homeRank": "137",
      "awayRank": "246",
      "tournamentLogo": "https://raw.githubusercontent.com/elfcrzgr/macsaati-backend/main/tennis/tournament_logos/34228.png",
      "homeScore": "-",
      "awayScore": "-",
      "setScores": "",
      "tournament": "Oeiras 4, Portugal"
    },
    {
      "id": 16065998,
      "isElite": true,
      "status": "notstarted",
      "fixedDate": "2026-04-26",
      "fixedTime": "13:10",
      "timestamp": 1777198200000,
      "broadcaster": "S Sport / beIN Sports",
      "homeTeam": {
        "name": "Tabilo A / Tien L",
        "logos": [
          "https://raw.githubusercontent.com/elfcrzgr/macsaati-backend/main/tennis/logos/cl.png",
          "https://raw.githubusercontent.com/elfcrzgr/macsaati-backend/main/tennis/logos/us.png"
        ]
      },
      "awayTeam": {
        "name": "Heliovaara H / Patten H",
        "logos": [
          "https://raw.githubusercontent.com/elfcrzgr/macsaati-backend/main/tennis/logos/fi.png",
          "https://raw.githubusercontent.com/elfcrzgr/macsaati-backend/main/tennis/logos/gb.png"
        ]
      },
      "homeRank": null,
      "awayRank": null,
      "tournamentLogo": "https://raw.githubusercontent.com/elfcrzgr/macsaati-backend/main/tennis/tournament_logos/2511.png",
      "homeScore": "-",
      "awayScore": "-",
      "setScores": "",
      "tournament": "Madrid, Spain, Doubles"
    },
    {
      "id": 16012163,
      "isElite": true,
      "status": "notstarted",
      "fixedDate": "2026-04-26",
      "fixedTime": "13:10",
      "timestamp": 1777198200000,
      "broadcaster": "S Sport / beIN Sports",
      "homeTeam": {
        "name": "Dino Prižmić",
        "logos": [
          "https://raw.githubusercontent.com/elfcrzgr/macsaati-backend/main/tennis/logos/hr.png"
        ]
      },
      "awayTeam": {
        "name": "Tomas Martin Etcheverry",
        "logos": [
          "https://raw.githubusercontent.com/elfcrzgr/macsaati-backend/main/tennis/logos/ar.png"
        ]
      },
      "homeRank": "87",
      "awayRank": "29",
      "tournamentLogo": "https://raw.githubusercontent.com/elfcrzgr/macsaati-backend/main/tennis/tournament_logos/2374.png",
      "homeScore": "-",
      "awayScore": "-",
      "setScores": "",
      "tournament": "Madrid, Spain"
    },
    {
      "id": 16013090,
      "isElite": true,
      "status": "notstarted",
      "fixedDate": "2026-04-26",
      "fixedTime": "13:10",
      "timestamp": 1777198200000,
      "broadcaster": "S Sport / beIN Sports",
      "homeTeam": {
        "name": "Tallon Griekspoor",
        "logos": [
          "https://raw.githubusercontent.com/elfcrzgr/macsaati-backend/main/tennis/logos/nl.png"
        ]
      },
      "awayTeam": {
        "name": "Lorenzo Musetti",
        "logos": [
          "https://raw.githubusercontent.com/elfcrzgr/macsaati-backend/main/tennis/logos/it.png"
        ]
      },
      "homeRank": "33",
      "awayRank": "9",
      "tournamentLogo": "https://raw.githubusercontent.com/elfcrzgr/macsaati-backend/main/tennis/tournament_logos/2374.png",
      "homeScore": "-",
      "awayScore": "-",
      "setScores": "",
      "tournament": "Madrid, Spain"
    },
    {
      "id": 16012115,
      "isElite": true,
      "status": "notstarted",
      "fixedDate": "2026-04-26",
      "fixedTime": "14:00",
      "timestamp": 1777201200000,
      "broadcaster": "S Sport / beIN Sports",
      "homeTeam": {
        "name": "Elise Mertens",
        "logos": [
          "https://raw.githubusercontent.com/elfcrzgr/macsaati-backend/main/tennis/logos/be.png"
        ]
      },
      "awayTeam": {
        "name": "Karolína Plíšková",
        "logos": [
          "https://raw.githubusercontent.com/elfcrzgr/macsaati-backend/main/tennis/logos/cz.png"
        ]
      },
      "homeRank": "21",
      "awayRank": "197",
      "tournamentLogo": "https://raw.githubusercontent.com/elfcrzgr/macsaati-backend/main/tennis/tournament_logos/2607.png",
      "homeScore": "-",
      "awayScore": "-",
      "setScores": "",
      "tournament": "Madrid, Spain"
    },
    {
      "id": 16012157,
      "isElite": true,
      "status": "notstarted",
      "fixedDate": "2026-04-26",
      "fixedTime": "14:20",
      "timestamp": 1777202400000,
      "broadcaster": "S Sport / beIN Sports",
      "homeTeam": {
        "name": "Arthur Fils",
        "logos": [
          "https://raw.githubusercontent.com/elfcrzgr/macsaati-backend/main/tennis/logos/fr.png"
        ]
      },
      "awayTeam": {
        "name": "Emilio Nava",
        "logos": [
          "https://raw.githubusercontent.com/elfcrzgr/macsaati-backend/main/tennis/logos/us.png"
        ]
      },
      "homeRank": "25",
      "awayRank": "116",
      "tournamentLogo": "https://raw.githubusercontent.com/elfcrzgr/macsaati-backend/main/tennis/tournament_logos/2374.png",
      "homeScore": "-",
      "awayScore": "-",
      "setScores": "",
      "tournament": "Madrid, Spain"
    },
    {
      "id": 16012126,
      "isElite": true,
      "status": "notstarted",
      "fixedDate": "2026-04-26",
      "fixedTime": "15:10",
      "timestamp": 1777205400000,
      "broadcaster": "S Sport / beIN Sports",
      "homeTeam": {
        "name": "Jessica Pegula",
        "logos": [
          "https://raw.githubusercontent.com/elfcrzgr/macsaati-backend/main/tennis/logos/us.png"
        ]
      },
      "awayTeam": {
        "name": "Marta Kostyuk",
        "logos": [
          "https://raw.githubusercontent.com/elfcrzgr/macsaati-backend/main/tennis/logos/ua.png"
        ]
      },
      "homeRank": "5",
      "awayRank": "23",
      "tournamentLogo": "https://raw.githubusercontent.com/elfcrzgr/macsaati-backend/main/tennis/tournament_logos/2607.png",
      "homeScore": "-",
      "awayScore": "-",
      "setScores": "",
      "tournament": "Madrid, Spain"
    },
    {
      "id": 16018910,
      "isElite": true,
      "status": "notstarted",
      "fixedDate": "2026-04-26",
      "fixedTime": "15:10",
      "timestamp": 1777205400000,
      "broadcaster": "S Sport / beIN Sports",
      "homeTeam": {
        "name": "Eikeri U / Gleason Q",
        "logos": [
          "https://raw.githubusercontent.com/elfcrzgr/macsaati-backend/main/tennis/logos/no.png",
          "https://raw.githubusercontent.com/elfcrzgr/macsaati-backend/main/tennis/logos/us.png"
        ]
      },
      "awayTeam": {
        "name": "Gauff C / Montgomery R",
        "logos": [
          "https://raw.githubusercontent.com/elfcrzgr/macsaati-backend/main/tennis/logos/us.png",
          "https://raw.githubusercontent.com/elfcrzgr/macsaati-backend/main/tennis/logos/us.png"
        ]
      },
      "homeRank": null,
      "awayRank": null,
      "tournamentLogo": "https://raw.githubusercontent.com/elfcrzgr/macsaati-backend/main/tennis/tournament_logos/2609.png",
      "homeScore": "-",
      "awayScore": "-",
      "setScores": "",
      "tournament": "Madrid, Spain, Doubles"
    },
    {
      "id": 16065999,
      "isElite": true,
      "status": "notstarted",
      "fixedDate": "2026-04-26",
      "fixedTime": "15:30",
      "timestamp": 1777206600000,
      "broadcaster": "S Sport / beIN Sports",
      "homeTeam": {
        "name": "Bublik A / Polmans M",
        "logos": [
          "https://raw.githubusercontent.com/elfcrzgr/macsaati-backend/main/tennis/logos/kz.png",
          "https://raw.githubusercontent.com/elfcrzgr/macsaati-backend/main/tennis/logos/au.png"
        ]
      },
      "awayTeam": {
        "name": "Luz O / Matos R",
        "logos": [
          "https://raw.githubusercontent.com/elfcrzgr/macsaati-backend/main/tennis/logos/br.png",
          "https://raw.githubusercontent.com/elfcrzgr/macsaati-backend/main/tennis/logos/br.png"
        ]
      },
      "homeRank": null,
      "awayRank": null,
      "tournamentLogo": "https://raw.githubusercontent.com/elfcrzgr/macsaati-backend/main/tennis/tournament_logos/2511.png",
      "homeScore": "-",
      "awayScore": "-",
      "setScores": "",
      "tournament": "Madrid, Spain, Doubles"
    },
    {
      "id": 16066011,
      "isElite": true,
      "status": "notstarted",
      "fixedDate": "2026-04-26",
      "fixedTime": "15:30",
      "timestamp": 1777206600000,
      "broadcaster": "S Sport / beIN Sports",
      "homeTeam": {
        "name": "Melo M / Zverev A",
        "logos": [
          "https://raw.githubusercontent.com/elfcrzgr/macsaati-backend/main/tennis/logos/br.png",
          "https://raw.githubusercontent.com/elfcrzgr/macsaati-backend/main/tennis/logos/de.png"
        ]
      },
      "awayTeam": {
        "name": "Darderi L / Tsitsipas S",
        "logos": [
          "https://raw.githubusercontent.com/elfcrzgr/macsaati-backend/main/tennis/logos/it.png",
          "https://raw.githubusercontent.com/elfcrzgr/macsaati-backend/main/tennis/logos/gr.png"
        ]
      },
      "homeRank": null,
      "awayRank": null,
      "tournamentLogo": "https://raw.githubusercontent.com/elfcrzgr/macsaati-backend/main/tennis/tournament_logos/2511.png",
      "homeScore": "-",
      "awayScore": "-",
      "setScores": "",
      "tournament": "Madrid, Spain, Doubles"
    },
    {
      "id": 16018907,
      "isElite": true,
      "status": "notstarted",
      "fixedDate": "2026-04-26",
      "fixedTime": "16:20",
      "timestamp": 1777209600000,
      "broadcaster": "S Sport / beIN Sports",
      "homeTeam": {
        "name": "Krunic A / Mladenovic K",
        "logos": [
          "https://raw.githubusercontent.com/elfcrzgr/macsaati-backend/main/tennis/logos/rs.png",
          "https://raw.githubusercontent.com/elfcrzgr/macsaati-backend/main/tennis/logos/fr.png"
        ]
      },
      "awayTeam": {
        "name": "Bouzkova M / Noskova L",
        "logos": [
          "https://raw.githubusercontent.com/elfcrzgr/macsaati-backend/main/tennis/logos/cz.png",
          "https://raw.githubusercontent.com/elfcrzgr/macsaati-backend/main/tennis/logos/cz.png"
        ]
      },
      "homeRank": null,
      "awayRank": null,
      "tournamentLogo": "https://raw.githubusercontent.com/elfcrzgr/macsaati-backend/main/tennis/tournament_logos/2609.png",
      "homeScore": "-",
      "awayScore": "-",
      "setScores": "",
      "tournament": "Madrid, Spain, Doubles"
    },
    {
      "id": 16066008,
      "isElite": true,
      "status": "notstarted",
      "fixedDate": "2026-04-26",
      "fixedTime": "16:40",
      "timestamp": 1777210800000,
      "broadcaster": "S Sport / beIN Sports",
      "homeTeam": {
        "name": "Cerundolo F / Etcheverry T",
        "logos": [
          "https://raw.githubusercontent.com/elfcrzgr/macsaati-backend/main/tennis/logos/ar.png",
          "https://raw.githubusercontent.com/elfcrzgr/macsaati-backend/main/tennis/logos/ar.png"
        ]
      },
      "awayTeam": {
        "name": "Cabral F / Salisbury J",
        "logos": [
          "https://raw.githubusercontent.com/elfcrzgr/macsaati-backend/main/tennis/logos/pt.png",
          "https://raw.githubusercontent.com/elfcrzgr/macsaati-backend/main/tennis/logos/gb.png"
        ]
      },
      "homeRank": null,
      "awayRank": null,
      "tournamentLogo": "https://raw.githubusercontent.com/elfcrzgr/macsaati-backend/main/tennis/tournament_logos/2511.png",
      "homeScore": "-",
      "awayScore": "-",
      "setScores": "",
      "tournament": "Madrid, Spain, Doubles"
    },
    {
      "id": 16066006,
      "isElite": true,
      "status": "notstarted",
      "fixedDate": "2026-04-26",
      "fixedTime": "16:40",
      "timestamp": 1777210800000,
      "broadcaster": "S Sport / beIN Sports",
      "homeTeam": {
        "name": "Krawietz K / Puetz T",
        "logos": [
          "https://raw.githubusercontent.com/elfcrzgr/macsaati-backend/main/tennis/logos/de.png",
          "https://raw.githubusercontent.com/elfcrzgr/macsaati-backend/main/tennis/logos/de.png"
        ]
      },
      "awayTeam": {
        "name": "Griekspoor T / Nakashima B",
        "logos": [
          "https://raw.githubusercontent.com/elfcrzgr/macsaati-backend/main/tennis/logos/nl.png",
          "https://raw.githubusercontent.com/elfcrzgr/macsaati-backend/main/tennis/logos/us.png"
        ]
      },
      "homeRank": null,
      "awayRank": null,
      "tournamentLogo": "https://raw.githubusercontent.com/elfcrzgr/macsaati-backend/main/tennis/tournament_logos/2511.png",
      "homeScore": "-",
      "awayScore": "-",
      "setScores": "",
      "tournament": "Madrid, Spain, Doubles"
    },
    {
      "id": 16012177,
      "isElite": true,
      "status": "notstarted",
      "fixedDate": "2026-04-26",
      "fixedTime": "17:00",
      "timestamp": 1777212000000,
      "broadcaster": "S Sport / beIN Sports",
      "homeTeam": {
        "name": "Jannik Sinner",
        "logos": [
          "https://raw.githubusercontent.com/elfcrzgr/macsaati-backend/main/tennis/logos/it.png"
        ]
      },
      "awayTeam": {
        "name": "Elmer Moller",
        "logos": [
          "https://raw.githubusercontent.com/elfcrzgr/macsaati-backend/main/tennis/logos/dk.png"
        ]
      },
      "homeRank": "1",
      "awayRank": "169",
      "tournamentLogo": "https://raw.githubusercontent.com/elfcrzgr/macsaati-backend/main/tennis/tournament_logos/2374.png",
      "homeScore": "-",
      "awayScore": "-",
      "setScores": "",
      "tournament": "Madrid, Spain"
    },
    {
      "id": 16018904,
      "isElite": true,
      "status": "notstarted",
      "fixedDate": "2026-04-26",
      "fixedTime": "17:30",
      "timestamp": 1777213800000,
      "broadcaster": "S Sport / beIN Sports",
      "homeTeam": {
        "name": "Sutjiadi A / Tjen J",
        "logos": [
          "https://raw.githubusercontent.com/elfcrzgr/macsaati-backend/main/tennis/logos/id.png",
          "https://raw.githubusercontent.com/elfcrzgr/macsaati-backend/main/tennis/logos/id.png"
        ]
      },
      "awayTeam": {
        "name": "Bucsa C / Melichar-Martinez N",
        "logos": [
          "https://raw.githubusercontent.com/elfcrzgr/macsaati-backend/main/tennis/logos/es.png",
          "https://raw.githubusercontent.com/elfcrzgr/macsaati-backend/main/tennis/logos/us.png"
        ]
      },
      "homeRank": null,
      "awayRank": null,
      "tournamentLogo": "https://raw.githubusercontent.com/elfcrzgr/macsaati-backend/main/tennis/tournament_logos/2609.png",
      "homeScore": "-",
      "awayScore": "-",
      "setScores": "",
      "tournament": "Madrid, Spain, Doubles"
    },
    {
      "id": 16066013,
      "isElite": true,
      "status": "notstarted",
      "fixedDate": "2026-04-26",
      "fixedTime": "17:50",
      "timestamp": 1777215000000,
      "broadcaster": "S Sport / beIN Sports",
      "homeTeam": {
        "name": "Bhambri Y / Venus M",
        "logos": [
          "https://raw.githubusercontent.com/elfcrzgr/macsaati-backend/main/tennis/logos/in.png",
          "https://raw.githubusercontent.com/elfcrzgr/macsaati-backend/main/tennis/logos/nz.png"
        ]
      },
      "awayTeam": {
        "name": "Erler A / Miedler L",
        "logos": [
          "https://raw.githubusercontent.com/elfcrzgr/macsaati-backend/main/tennis/logos/at.png",
          "https://raw.githubusercontent.com/elfcrzgr/macsaati-backend/main/tennis/logos/at.png"
        ]
      },
      "homeRank": null,
      "awayRank": null,
      "tournamentLogo": "https://raw.githubusercontent.com/elfcrzgr/macsaati-backend/main/tennis/tournament_logos/2511.png",
      "homeScore": "-",
      "awayScore": "-",
      "setScores": "",
      "tournament": "Madrid, Spain, Doubles"
    },
    {
      "id": 16012170,
      "isElite": true,
      "status": "notstarted",
      "fixedDate": "2026-04-26",
      "fixedTime": "18:30",
      "timestamp": 1777217400000,
      "broadcaster": "S Sport / beIN Sports",
      "homeTeam": {
        "name": "Cameron Norrie",
        "logos": [
          "https://raw.githubusercontent.com/elfcrzgr/macsaati-backend/main/tennis/logos/gb.png"
        ]
      },
      "awayTeam": {
        "name": "Thiago Agustin Tirante",
        "logos": [
          "https://raw.githubusercontent.com/elfcrzgr/macsaati-backend/main/tennis/logos/ar.png"
        ]
      },
      "homeRank": "23",
      "awayRank": "75",
      "tournamentLogo": "https://raw.githubusercontent.com/elfcrzgr/macsaati-backend/main/tennis/tournament_logos/2374.png",
      "homeScore": "-",
      "awayScore": "-",
      "setScores": "",
      "tournament": "Madrid, Spain"
    },
    {
      "id": 16066000,
      "isElite": true,
      "status": "notstarted",
      "fixedDate": "2026-04-26",
      "fixedTime": "19:40",
      "timestamp": 1777221600000,
      "broadcaster": "S Sport / beIN Sports",
      "homeTeam": {
        "name": "Arribage T / Olivetti A",
        "logos": [
          "https://raw.githubusercontent.com/elfcrzgr/macsaati-backend/main/tennis/logos/fr.png",
          "https://raw.githubusercontent.com/elfcrzgr/macsaati-backend/main/tennis/logos/fr.png"
        ]
      },
      "awayTeam": {
        "name": "Carreno Busta P / Cervantes I",
        "logos": [
          "https://raw.githubusercontent.com/elfcrzgr/macsaati-backend/main/tennis/logos/es.png",
          "https://raw.githubusercontent.com/elfcrzgr/macsaati-backend/main/tennis/logos/es.png"
        ]
      },
      "homeRank": null,
      "awayRank": null,
      "tournamentLogo": "https://raw.githubusercontent.com/elfcrzgr/macsaati-backend/main/tennis/tournament_logos/2511.png",
      "homeScore": "-",
      "awayScore": "-",
      "setScores": "",
      "tournament": "Madrid, Spain, Doubles"
    },
    {
      "id": 16012165,
      "isElite": true,
      "status": "notstarted",
      "fixedDate": "2026-04-26",
      "fixedTime": "20:00",
      "timestamp": 1777222800000,
      "broadcaster": "S Sport / beIN Sports",
      "homeTeam": {
        "name": "Vit Kopřiva",
        "logos": [
          "https://raw.githubusercontent.com/elfcrzgr/macsaati-backend/main/tennis/logos/cz.png"
        ]
      },
      "awayTeam": {
        "name": "Arthur Rinderknech",
        "logos": [
          "https://raw.githubusercontent.com/elfcrzgr/macsaati-backend/main/tennis/logos/fr.png"
        ]
      },
      "homeRank": "66",
      "awayRank": "26",
      "tournamentLogo": "https://raw.githubusercontent.com/elfcrzgr/macsaati-backend/main/tennis/tournament_logos/2374.png",
      "homeScore": "-",
      "awayScore": "-",
      "setScores": "",
      "tournament": "Madrid, Spain"
    },
    {
      "id": 16012118,
      "isElite": true,
      "status": "notstarted",
      "fixedDate": "2026-04-26",
      "fixedTime": "21:00",
      "timestamp": 1777226400000,
      "broadcaster": "S Sport / beIN Sports",
      "homeTeam": {
        "name": "Qinwen Zheng",
        "logos": [
          "https://raw.githubusercontent.com/elfcrzgr/macsaati-backend/main/tennis/logos/cn.png"
        ]
      },
      "awayTeam": {
        "name": "Elena Rybakina",
        "logos": [
          "https://raw.githubusercontent.com/elfcrzgr/macsaati-backend/main/tennis/logos/kz.png"
        ]
      },
      "homeRank": "36",
      "awayRank": "2",
      "tournamentLogo": "https://raw.githubusercontent.com/elfcrzgr/macsaati-backend/main/tennis/tournament_logos/2607.png",
      "homeScore": "-",
      "awayScore": "-",
      "setScores": "",
      "tournament": "Madrid, Spain"
    },
    {
      "id": 16012167,
      "isElite": true,
      "status": "notstarted",
      "fixedDate": "2026-04-26",
      "fixedTime": "22:10",
      "timestamp": 1777230600000,
      "broadcaster": "S Sport / beIN Sports",
      "homeTeam": {
        "name": "Joao Fonseca",
        "logos": [
          "https://raw.githubusercontent.com/elfcrzgr/macsaati-backend/main/tennis/logos/br.png"
        ]
      },
      "awayTeam": {
        "name": "Rafael Jodar",
        "logos": [
          "https://raw.githubusercontent.com/elfcrzgr/macsaati-backend/main/tennis/logos/es.png"
        ]
      },
      "homeRank": "31",
      "awayRank": "42",
      "tournamentLogo": "https://raw.githubusercontent.com/elfcrzgr/macsaati-backend/main/tennis/tournament_logos/2374.png",
      "homeScore": "-",
      "awayScore": "-",
      "setScores": "",
      "tournament": "Madrid, Spain"
    },
    {
      "id": 16012121,
      "isElite": true,
      "status": "notstarted",
      "fixedDate": "2026-04-26",
      "fixedTime": "22:30",
      "timestamp": 1777231800000,
      "broadcaster": "S Sport / beIN Sports",
      "homeTeam": {
        "name": "Anastasia Potapova",
        "logos": [
          "https://raw.githubusercontent.com/elfcrzgr/macsaati-backend/main/tennis/logos/at.png"
        ]
      },
      "awayTeam": {
        "name": "Jelena Ostapenko",
        "logos": [
          "https://raw.githubusercontent.com/elfcrzgr/macsaati-backend/main/tennis/logos/lv.png"
        ]
      },
      "homeRank": "56",
      "awayRank": "40",
      "tournamentLogo": "https://raw.githubusercontent.com/elfcrzgr/macsaati-backend/main/tennis/tournament_logos/2607.png",
      "homeScore": "-",
      "awayScore": "-",
      "setScores": "",
      "tournament": "Madrid, Spain"
    },
    {
      "id": 16066010,
      "isElite": true,
      "status": "notstarted",
      "fixedDate": "2026-04-27",
      "fixedTime": "12:00",
      "timestamp": 1777280400000,
      "broadcaster": "S Sport / beIN Sports",
      "homeTeam": {
        "name": "Andreozzi G / Guinard M",
        "logos": [
          "https://raw.githubusercontent.com/elfcrzgr/macsaati-backend/main/tennis/logos/ar.png",
          "https://raw.githubusercontent.com/elfcrzgr/macsaati-backend/main/tennis/logos/fr.png"
        ]
      },
      "awayTeam": {
        "name": "Bolelli S / Vavassori A",
        "logos": [
          "https://raw.githubusercontent.com/elfcrzgr/macsaati-backend/main/tennis/logos/it.png",
          "https://raw.githubusercontent.com/elfcrzgr/macsaati-backend/main/tennis/logos/it.png"
        ]
      },
      "homeRank": null,
      "awayRank": null,
      "tournamentLogo": "https://raw.githubusercontent.com/elfcrzgr/macsaati-backend/main/tennis/tournament_logos/2511.png",
      "homeScore": "-",
      "awayScore": "-",
      "setScores": "",
      "tournament": "Madrid, Spain, Doubles"
    },
    {
      "id": 16066005,
      "isElite": true,
      "status": "notstarted",
      "fixedDate": "2026-04-27",
      "fixedTime": "12:00",
      "timestamp": 1777280400000,
      "broadcaster": "S Sport / beIN Sports",
      "homeTeam": {
        "name": "Arends S / Pel D",
        "logos": [
          "https://raw.githubusercontent.com/elfcrzgr/macsaati-backend/main/tennis/logos/nl.png",
          "https://raw.githubusercontent.com/elfcrzgr/macsaati-backend/main/tennis/logos/nl.png"
        ]
      },
      "awayTeam": {
        "name": "Goransson A / King E",
        "logos": [
          "https://raw.githubusercontent.com/elfcrzgr/macsaati-backend/main/tennis/logos/se.png",
          "https://raw.githubusercontent.com/elfcrzgr/macsaati-backend/main/tennis/logos/us.png"
        ]
      },
      "homeRank": null,
      "awayRank": null,
      "tournamentLogo": "https://raw.githubusercontent.com/elfcrzgr/macsaati-backend/main/tennis/tournament_logos/2511.png",
      "homeScore": "-",
      "awayScore": "-",
      "setScores": "",
      "tournament": "Madrid, Spain, Doubles"
    },
    {
      "id": 16066002,
      "isElite": true,
      "status": "notstarted",
      "fixedDate": "2026-04-27",
      "fixedTime": "12:00",
      "timestamp": 1777280400000,
      "broadcaster": "S Sport / beIN Sports",
      "homeTeam": {
        "name": "Doumbia S / Reboul F",
        "logos": [
          "https://raw.githubusercontent.com/elfcrzgr/macsaati-backend/main/tennis/logos/fr.png",
          "https://raw.githubusercontent.com/elfcrzgr/macsaati-backend/main/tennis/logos/fr.png"
        ]
      },
      "awayTeam": {
        "name": "Cash J / Glasspool L",
        "logos": [
          "https://raw.githubusercontent.com/elfcrzgr/macsaati-backend/main/tennis/logos/gb.png",
          "https://raw.githubusercontent.com/elfcrzgr/macsaati-backend/main/tennis/logos/gb.png"
        ]
      },
      "homeRank": null,
      "awayRank": null,
      "tournamentLogo": "https://raw.githubusercontent.com/elfcrzgr/macsaati-backend/main/tennis/tournament_logos/2511.png",
      "homeScore": "-",
      "awayScore": "-",
      "setScores": "",
      "tournament": "Madrid, Spain, Doubles"
    },
    {
      "id": 16066009,
      "isElite": true,
      "status": "notstarted",
      "fixedDate": "2026-04-27",
      "fixedTime": "12:00",
      "timestamp": 1777280400000,
      "broadcaster": "S Sport / beIN Sports",
      "homeTeam": {
        "name": "Harrison C / Skupski N",
        "logos": [
          "https://raw.githubusercontent.com/elfcrzgr/macsaati-backend/main/tennis/logos/us.png",
          "https://raw.githubusercontent.com/elfcrzgr/macsaati-backend/main/tennis/logos/gb.png"
        ]
      },
      "awayTeam": {
        "name": "Cash R / Tracy J",
        "logos": [
          "https://raw.githubusercontent.com/elfcrzgr/macsaati-backend/main/tennis/logos/us.png",
          "https://raw.githubusercontent.com/elfcrzgr/macsaati-backend/main/tennis/logos/us.png"
        ]
      },
      "homeRank": null,
      "awayRank": null,
      "tournamentLogo": "https://raw.githubusercontent.com/elfcrzgr/macsaati-backend/main/tennis/tournament_logos/2511.png",
      "homeScore": "-",
      "awayScore": "-",
      "setScores": "",
      "tournament": "Madrid, Spain, Doubles"
    },
    {
      "id": 16066001,
      "isElite": true,
      "status": "notstarted",
      "fixedDate": "2026-04-27",
      "fixedTime": "12:00",
      "timestamp": 1777280400000,
      "broadcaster": "S Sport / beIN Sports",
      "homeTeam": {
        "name": "Llamas Ruiz P / Winter López B",
        "logos": [
          "https://raw.githubusercontent.com/elfcrzgr/macsaati-backend/main/tennis/logos/es.png",
          "https://raw.githubusercontent.com/elfcrzgr/macsaati-backend/main/tennis/logos/es.png"
        ]
      },
      "awayTeam": {
        "name": "Krajicek A / Mektic N",
        "logos": [
          "https://raw.githubusercontent.com/elfcrzgr/macsaati-backend/main/tennis/logos/us.png",
          "https://raw.githubusercontent.com/elfcrzgr/macsaati-backend/main/tennis/logos/hr.png"
        ]
      },
      "homeRank": null,
      "awayRank": null,
      "tournamentLogo": "https://raw.githubusercontent.com/elfcrzgr/macsaati-backend/main/tennis/tournament_logos/2511.png",
      "homeScore": "-",
      "awayScore": "-",
      "setScores": "",
      "tournament": "Madrid, Spain, Doubles"
    },
    {
      "id": 16066007,
      "isElite": true,
      "status": "notstarted",
      "fixedDate": "2026-04-27",
      "fixedTime": "12:00",
      "timestamp": 1777280400000,
      "broadcaster": "S Sport / beIN Sports",
      "homeTeam": {
        "name": "Moutet C / Rinderknech A",
        "logos": [
          "https://raw.githubusercontent.com/elfcrzgr/macsaati-backend/main/tennis/logos/fr.png",
          "https://raw.githubusercontent.com/elfcrzgr/macsaati-backend/main/tennis/logos/fr.png"
        ]
      },
      "awayTeam": {
        "name": "Johnson L / Zielinski J",
        "logos": [
          "https://raw.githubusercontent.com/elfcrzgr/macsaati-backend/main/tennis/logos/gb.png",
          "https://raw.githubusercontent.com/elfcrzgr/macsaati-backend/main/tennis/logos/pl.png"
        ]
      },
      "homeRank": null,
      "awayRank": null,
      "tournamentLogo": "https://raw.githubusercontent.com/elfcrzgr/macsaati-backend/main/tennis/tournament_logos/2511.png",
      "homeScore": "-",
      "awayScore": "-",
      "setScores": "",
      "tournament": "Madrid, Spain, Doubles"
    },
    {
      "id": 16066004,
      "isElite": true,
      "status": "notstarted",
      "fixedDate": "2026-04-27",
      "fixedTime": "12:00",
      "timestamp": 1777280400000,
      "broadcaster": "S Sport / beIN Sports",
      "homeTeam": {
        "name": "Nys H / Roger-Vasselin E",
        "logos": [
          "https://raw.githubusercontent.com/elfcrzgr/macsaati-backend/main/tennis/logos/mc.png",
          "https://raw.githubusercontent.com/elfcrzgr/macsaati-backend/main/tennis/logos/fr.png"
        ]
      },
      "awayTeam": {
        "name": "Gonzalez M / Molteni A",
        "logos": [
          "https://raw.githubusercontent.com/elfcrzgr/macsaati-backend/main/tennis/logos/ar.png",
          "https://raw.githubusercontent.com/elfcrzgr/macsaati-backend/main/tennis/logos/ar.png"
        ]
      },
      "homeRank": null,
      "awayRank": null,
      "tournamentLogo": "https://raw.githubusercontent.com/elfcrzgr/macsaati-backend/main/tennis/tournament_logos/2511.png",
      "homeScore": "-",
      "awayScore": "-",
      "setScores": "",
      "tournament": "Madrid, Spain, Doubles"
    },
    {
      "id": 16013088,
      "isElite": true,
      "status": "notstarted",
      "fixedDate": "2026-04-27",
      "fixedTime": "12:00",
      "timestamp": 1777280400000,
      "broadcaster": "S Sport / beIN Sports",
      "homeTeam": {
        "name": "Alejandro Davidovich Fokina",
        "logos": [
          "https://raw.githubusercontent.com/elfcrzgr/macsaati-backend/main/tennis/logos/es.png"
        ]
      },
      "awayTeam": {
        "name": "Casper Ruud",
        "logos": [
          "https://raw.githubusercontent.com/elfcrzgr/macsaati-backend/main/tennis/logos/no.png"
        ]
      },
      "homeRank": "24",
      "awayRank": "15",
      "tournamentLogo": "https://raw.githubusercontent.com/elfcrzgr/macsaati-backend/main/tennis/tournament_logos/2374.png",
      "homeScore": "-",
      "awayScore": "-",
      "setScores": "",
      "tournament": "Madrid, Spain"
    },
    {
      "id": 16013101,
      "isElite": true,
      "status": "notstarted",
      "fixedDate": "2026-04-27",
      "fixedTime": "12:00",
      "timestamp": 1777280400000,
      "broadcaster": "S Sport / beIN Sports",
      "homeTeam": {
        "name": "Francisco Cerundolo",
        "logos": [
          "https://raw.githubusercontent.com/elfcrzgr/macsaati-backend/main/tennis/logos/ar.png"
        ]
      },
      "awayTeam": {
        "name": "Luciano Darderi",
        "logos": [
          "https://raw.githubusercontent.com/elfcrzgr/macsaati-backend/main/tennis/logos/it.png"
        ]
      },
      "homeRank": "20",
      "awayRank": "22",
      "tournamentLogo": "https://raw.githubusercontent.com/elfcrzgr/macsaati-backend/main/tennis/tournament_logos/2374.png",
      "homeScore": "-",
      "awayScore": "-",
      "setScores": "",
      "tournament": "Madrid, Spain"
    },
    {
      "id": 16013079,
      "isElite": true,
      "status": "notstarted",
      "fixedDate": "2026-04-27",
      "fixedTime": "12:00",
      "timestamp": 1777280400000,
      "broadcaster": "S Sport / beIN Sports",
      "homeTeam": {
        "name": "Karen Khachanov",
        "logos": [
          "https://raw.githubusercontent.com/elfcrzgr/macsaati-backend/main/tennis/logos/ru.png"
        ]
      },
      "awayTeam": {
        "name": "Jakub Menšik",
        "logos": [
          "https://raw.githubusercontent.com/elfcrzgr/macsaati-backend/main/tennis/logos/cz.png"
        ]
      },
      "homeRank": "16",
      "awayRank": "27",
      "tournamentLogo": "https://raw.githubusercontent.com/elfcrzgr/macsaati-backend/main/tennis/tournament_logos/2374.png",
      "homeScore": "-",
      "awayScore": "-",
      "setScores": "",
      "tournament": "Madrid, Spain"
    },
    {
      "id": 16012116,
      "isElite": true,
      "status": "notstarted",
      "fixedDate": "2026-04-27",
      "fixedTime": "12:00",
      "timestamp": 1777280400000,
      "broadcaster": "S Sport / beIN Sports",
      "homeTeam": {
        "name": "Mirra Andreeva",
        "logos": [
          "https://raw.githubusercontent.com/elfcrzgr/macsaati-backend/main/tennis/logos/ru.png"
        ]
      },
      "awayTeam": {
        "name": "Anna Bondar",
        "logos": [
          "https://raw.githubusercontent.com/elfcrzgr/macsaati-backend/main/tennis/logos/hu.png"
        ]
      },
      "homeRank": "8",
      "awayRank": "63",
      "tournamentLogo": "https://raw.githubusercontent.com/elfcrzgr/macsaati-backend/main/tennis/tournament_logos/2607.png",
      "homeScore": "-",
      "awayScore": "-",
      "setScores": "",
      "tournament": "Madrid, Spain"
    },
    {
      "id": 16018906,
      "isElite": true,
      "status": "notstarted",
      "fixedDate": "2026-04-27",
      "fixedTime": "12:00",
      "timestamp": 1777280400000,
      "broadcaster": "S Sport / beIN Sports",
      "homeTeam": {
        "name": "Hsieh S-W / Kenin S",
        "logos": [
          "https://raw.githubusercontent.com/elfcrzgr/macsaati-backend/main/tennis/logos/tw.png",
          "https://raw.githubusercontent.com/elfcrzgr/macsaati-backend/main/tennis/logos/us.png"
        ]
      },
      "awayTeam": {
        "name": "Boulter K / Williams V",
        "logos": [
          "https://raw.githubusercontent.com/elfcrzgr/macsaati-backend/main/tennis/logos/gb.png",
          "https://raw.githubusercontent.com/elfcrzgr/macsaati-backend/main/tennis/logos/us.png"
        ]
      },
      "homeRank": null,
      "awayRank": null,
      "tournamentLogo": "https://raw.githubusercontent.com/elfcrzgr/macsaati-backend/main/tennis/tournament_logos/2609.png",
      "homeScore": "-",
      "awayScore": "-",
      "setScores": "",
      "tournament": "Madrid, Spain, Doubles"
    },
    {
      "id": 16018909,
      "isElite": true,
      "status": "notstarted",
      "fixedDate": "2026-04-27",
      "fixedTime": "12:00",
      "timestamp": 1777280400000,
      "broadcaster": "S Sport / beIN Sports",
      "homeTeam": {
        "name": "Kozyreva M / Skoch M",
        "logos": [
          "https://raw.githubusercontent.com/elfcrzgr/macsaati-backend/main/tennis/logos/ru.png",
          "https://raw.githubusercontent.com/elfcrzgr/macsaati-backend/main/tennis/logos/cz.png"
        ]
      },
      "awayTeam": {
        "name": "Perez E / Schuurs D",
        "logos": [
          "https://raw.githubusercontent.com/elfcrzgr/macsaati-backend/main/tennis/logos/au.png",
          "https://raw.githubusercontent.com/elfcrzgr/macsaati-backend/main/tennis/logos/nl.png"
        ]
      },
      "homeRank": null,
      "awayRank": null,
      "tournamentLogo": "https://raw.githubusercontent.com/elfcrzgr/macsaati-backend/main/tennis/tournament_logos/2609.png",
      "homeScore": "-",
      "awayScore": "-",
      "setScores": "",
      "tournament": "Madrid, Spain, Doubles"
    }
  ]
}